{"image_id": "potholes212", "proposals": [{"bbox": [244, 142, 292, 165], "label": "background", "iou": 0.06445586174684727}, {"bbox": [0, 283, 26, 323], "label": "background", "iou": 0.0}, {"bbox": [135, 96, 159, 114], "label": "background", "iou": 0.01245674740484429}, {"bbox": [62, 334, 115, 371], "label": "background", "iou": 0.0}, {"bbox": [263, 142, 292, 163], "label": "background", "iou": 0.06338028169014084}, {"bbox": [195, 121, 300, 221], "label": "background", "iou": 0.24531422271223816}, {"bbox": [146, 26, 167, 46], "label": "background", "iou": 0.0}, {"bbox": [168, 233, 189, 254], "label": "background", "iou": 0.012716262975778547}, {"bbox": [280, 70, 304, 104], "label": "background", "iou": 0.10085728693898134}, {"bbox": [116, 133, 151, 151], "label": "background", "iou": 0.018166089965397925}, {"bbox": [87, 167, 114, 188], "label": "background", "iou": 0.016349480968858132}, {"bbox": [122, 294, 172, 332], "label": "background", "iou": 0.0}, {"bbox": [0, 0, 400, 400], "label": "background", "iou": 0.21675}, {"bbox": [21, 271, 45, 293], "label": "background", "iou": 0.0}, {"bbox": [379, 25, 400, 63], "label": "background", "iou": 0.0}, {"bbox": [134, 95, 159, 117], "label": "background", "iou": 0.015859284890426758}, {"bbox": [36, 0, 94, 20], "label": "background", "iou": 0.0}, {"bbox": [30, 174, 50, 196], "label": "background", "iou": 0.0}, {"bbox": [198, 373, 237, 400], "label": "background", "iou": 0.0}, {"bbox": [80, 142, 216, 214], "label": "background", "iou": 0.2823529411764706}, {"bbox": [0, 194, 22, 216], "label": "background", "iou": 0.0}, {"bbox": [24, 79, 160, 213], "label": "background", "iou": 0.219435736677116}, {"bbox": [24, 360, 52, 392], "label": "background", "iou": 0.0}, {"bbox": [143, 125, 274, 189], "label": "background", "iou": 0.2417531718569781}, {"bbox": [42, 319, 137, 371], "label": "background", "iou": 0.0}, {"bbox": [75, 335, 115, 371], "label": "background", "iou": 0.0}, {"bbox": [196, 362, 237, 400], "label": "background", "iou": 0.0}, {"bbox": [117, 139, 141, 158], "label": "background", "iou": 0.01314878892733564}, {"bbox": [37, 218, 63, 237], "label": "background", "iou": 0.0}, {"bbox": [79, 338, 116, 354], "label": "background", "iou": 0.0}, {"bbox": [39, 189, 95, 237], "label": "background", "iou": 0.019646365422396856}, {"bbox": [20, 360, 55, 388], "label": "background", "iou": 0.0}, {"bbox": [286, 372, 306, 400], "label": "background", "iou": 0.0}, {"bbox": [225, 146, 292, 190], "label": "background", "iou": 0.07410367663850194}, {"bbox": [163, 0, 223, 39], "label": "background", "iou": 0.0}, {"bbox": [342, 237, 374, 271], "label": "background", "iou": 0.0}, {"bbox": [199, 140, 234, 161], "label": "background", "iou": 0.021193771626297576}, {"bbox": [192, 140, 274, 189], "label": "background", "iou": 0.11585928489042675}, {"bbox": [0, 183, 27, 216], "label": "background", "iou": 0.0}, {"bbox": [155, 0, 223, 39], "label": "background", "iou": 0.0}, {"bbox": [201, 186, 234, 205], "label": "background", "iou": 0.018079584775086505}, {"bbox": [0, 166, 56, 215], "label": "background", "iou": 0.0}, {"bbox": [118, 59, 140, 78], "label": "background", "iou": 0.0}, {"bbox": [54, 70, 141, 155], "label": "background", "iou": 0.09701726025968609}, {"bbox": [327, 25, 400, 135], "label": "background", "iou": 0.0424146027418011}, {"bbox": [303, 321, 322, 347], "label": "background", "iou": 0.0}, {"bbox": [252, 233, 400, 400], "label": "background", "iou": 0.016985138004246284}, {"bbox": [340, 126, 360, 151], "label": "background", "iou": 0.0}, {"bbox": [264, 132, 302, 171], "label": "background", "iou": 0.1729800032515038}, {"bbox": [117, 168, 152, 184], "label": "background", "iou": 0.016147635524798153}, {"bbox": [99, 311, 136, 335], "label": "background", "iou": 0.0}, {"bbox": [0, 367, 36, 400], "label": "background", "iou": 0.0}, {"bbox": [146, 15, 185, 46], "label": "background", "iou": 0.0}, {"bbox": [0, 193, 23, 216], "label": "background", "iou": 0.0}, {"bbox": [39, 218, 65, 237], "label": "background", "iou": 0.0}, {"bbox": [250, 331, 284, 374], "label": "background", "iou": 0.0}, {"bbox": [244, 152, 274, 172], "label": "background", "iou": 0.01730103806228374}, {"bbox": [301, 321, 322, 356], "label": "background", "iou": 0.0}, {"bbox": [257, 153, 282, 172], "label": "background", "iou": 0.022397891963109356}, {"bbox": [0, 369, 36, 400], "label": "background", "iou": 0.0}, {"bbox": [146, 0, 224, 46], "label": "background", "iou": 0.0}, {"bbox": [93, 69, 347, 224], "label": "pothole", "iou": 0.504469727752946}, {"bbox": [138, 285, 165, 300], "label": "background", "iou": 0.0}, {"bbox": [87, 76, 123, 100], "label": "background", "iou": 0.006114130434782609}, {"bbox": [364, 64, 388, 95], "label": "background", "iou": 0.0}, {"bbox": [110, 202, 132, 225], "label": "background", "iou": 0.014590542099192617}, {"bbox": [0, 183, 23, 216], "label": "background", "iou": 0.0}, {"bbox": [173, 103, 287, 156], "label": "background", "iou": 0.1688624817015414}, {"bbox": [86, 228, 116, 249], "label": "background", "iou": 0.018166089965397925}, {"bbox": [313, 275, 331, 316], "label": "background", "iou": 0.0}, {"bbox": [24, 361, 51, 380], "label": "background", "iou": 0.0}, {"bbox": [0, 283, 27, 325], "label": "background", "iou": 0.0}, {"bbox": [0, 0, 23, 28], "label": "background", "iou": 0.0}, {"bbox": [248, 309, 280, 345], "label": "background", "iou": 0.0}, {"bbox": [61, 229, 116, 257], "label": "background", "iou": 0.028626604566625014}, {"bbox": [136, 253, 158, 274], "label": "background", "iou": 0.006934097421203439}, {"bbox": [0, 0, 400, 206], "label": "background", "iou": 0.2424654045334918}, {"bbox": [199, 124, 235, 157], "label": "background", "iou": 0.0342560553633218}, {"bbox": [0, 103, 160, 369], "label": "background", "iou": 0.20012430080795526}, {"bbox": [150, 226, 186, 261], "label": "background", "iou": 0.03633217993079585}, {"bbox": [264, 132, 300, 171], "label": "background", "iou": 0.160676532769556}, {"bbox": [268, 142, 291, 170], "label": "background", "iou": 0.08066429418742586}, {"bbox": [0, 79, 182, 400], "label": "background", "iou": 0.22887463372139066}, {"bbox": [66, 317, 136, 380], "label": "background", "iou": 0.0}, {"bbox": [264, 142, 292, 171], "label": "background", "iou": 0.08342989571263036}, {"bbox": [76, 162, 114, 193], "label": "background", "iou": 0.03028387541661878}, {"bbox": [99, 211, 126, 228], "label": "background", "iou": 0.013235294117647059}, {"bbox": [356, 297, 400, 400], "label": "background", "iou": 0.0}, {"bbox": [0, 366, 36, 400], "label": "background", "iou": 0.0}, {"bbox": [221, 33, 400, 344], "label": "background", "iou": 0.13448184934517007}, {"bbox": [86, 76, 141, 111], "label": "background", "iou": 0.02621250350434539}, {"bbox": [382, 37, 400, 68], "label": "background", "iou": 0.0}, {"bbox": [264, 146, 292, 170], "label": "background", "iou": 0.07232546459065796}, {"bbox": [0, 79, 165, 375], "label": "background", "iou": 0.2092080498045461}, {"bbox": [195, 186, 233, 217], "label": "background", "iou": 0.0339677047289504}, {"bbox": [155, 81, 372, 400], "label": "background", "iou": 0.26752711258585143}, {"bbox": [54, 70, 141, 157], "label": "background", "iou": 0.10006249023590064}, {"bbox": [24, 79, 112, 162], "label": "background", "iou": 0.05466237942122187}, {"bbox": [0, 360, 54, 400], "label": "background", "iou": 0.0}, {"bbox": [24, 360, 52, 386], "label": "background", "iou": 0.0}, {"bbox": [264, 132, 303, 171], "label": "background", "iou": 0.1791287386215865}, {"bbox": [22, 81, 400, 400], "label": "background", "iou": 0.2876051151913221}, {"bbox": [267, 146, 292, 171], "label": "background", "iou": 0.07289908876139048}, {"bbox": [87, 70, 135, 100], "label": "background", "iou": 0.008037508372404554}, {"bbox": [356, 335, 382, 356], "label": "background", "iou": 0.0}, {"bbox": [354, 244, 374, 264], "label": "background", "iou": 0.0}, {"bbox": [61, 329, 116, 380], "label": "background", "iou": 0.0}, {"bbox": [62, 330, 115, 371], "label": "background", "iou": 0.0}, {"bbox": [87, 171, 113, 188], "label": "background", "iou": 0.012745098039215686}, {"bbox": [101, 93, 159, 117], "label": "background", "iou": 0.038401750244688816}, {"bbox": [323, 134, 356, 168], "label": "background", "iou": 0.07461984637090453}, {"bbox": [193, 140, 274, 221], "label": "background", "iou": 0.18918685121107268}, {"bbox": [153, 225, 185, 263], "label": "background", "iou": 0.035063437139561705}, {"bbox": [0, 151, 57, 216], "label": "background", "iou": 0.0}, {"bbox": [261, 340, 282, 362], "label": "background", "iou": 0.0}, {"bbox": [225, 154, 276, 185], "label": "background", "iou": 0.045588235294117645}, {"bbox": [183, 184, 233, 221], "label": "background", "iou": 0.05334486735870819}, {"bbox": [39, 209, 83, 237], "label": "background", "iou": 0.0023445350005582228}, {"bbox": [384, 92, 400, 126], "label": "background", "iou": 0.0}, {"bbox": [288, 327, 323, 368], "label": "background", "iou": 0.0}, {"bbox": [0, 81, 400, 400], "label": "background", "iou": 0.2717868338557994}, {"bbox": [131, 225, 185, 281], "label": "background", "iou": 0.05916062700151694}, {"bbox": [119, 46, 356, 171], "label": "background", "iou": 0.24622093023255814}, {"bbox": [250, 327, 284, 373], "label": "background", "iou": 0.0}, {"bbox": [62, 321, 115, 371], "label": "background", "iou": 0.0}, {"bbox": [47, 115, 107, 155], "label": "background", "iou": 0.03}, {"bbox": [21, 319, 182, 400], "label": "background", "iou": 0.0}, {"bbox": [308, 47, 339, 81], "label": "background", "iou": 0.008619408530242236}, {"bbox": [71, 98, 112, 135], "label": "background", "iou": 0.033816011195841544}, {"bbox": [0, 79, 179, 380], "label": "background", "iou": 0.23463313304242356}, {"bbox": [163, 179, 223, 239], "label": "background", "iou": 0.10380622837370242}, {"bbox": [225, 158, 274, 185], "label": "background", "iou": 0.03814878892733564}, {"bbox": [195, 124, 273, 221], "label": "background", "iou": 0.21816608996539794}, {"bbox": [249, 275, 340, 400], "label": "background", "iou": 0.0}, {"bbox": [381, 242, 400, 264], "label": "background", "iou": 0.0}, {"bbox": [274, 132, 303, 149], "label": "background", "iou": 0.08599337170765742}, {"bbox": [67, 319, 137, 353], "label": "background", "iou": 0.0}, {"bbox": [183, 197, 218, 221], "label": "background", "iou": 0.02422145328719723}, {"bbox": [362, 80, 386, 112], "label": "background", "iou": 0.0}, {"bbox": [301, 80, 336, 95], "label": "background", "iou": 0.09157509157509157}, {"bbox": [205, 154, 274, 190], "label": "background", "iou": 0.07162629757785467}, {"bbox": [24, 76, 142, 162], "label": "background", "iou": 0.10381168127647}, {"bbox": [320, 98, 364, 167], "label": "background", "iou": 0.15442338072669826}, {"bbox": [296, 275, 333, 347], "label": "background", "iou": 0.0}, {"bbox": [62, 334, 116, 371], "label": "background", "iou": 0.0}, {"bbox": [48, 340, 72, 360], "label": "background", "iou": 0.0}, {"bbox": [301, 321, 322, 348], "label": "background", "iou": 0.0}, {"bbox": [122, 0, 400, 113], "label": "background", "iou": 0.061191258391658336}, {"bbox": [139, 112, 274, 189], "label": "background", "iou": 0.29974048442906576}, {"bbox": [153, 226, 174, 247], "label": "background", "iou": 0.012716262975778547}, {"bbox": [0, 184, 154, 369], "label": "background", "iou": 0.1034061135371179}, {"bbox": [224, 122, 247, 145], "label": "background", "iou": 0.015253748558246828}, {"bbox": [75, 338, 105, 371], "label": "background", "iou": 0.0}, {"bbox": [264, 142, 292, 163], "label": "background", "iou": 0.0636042402826855}, {"bbox": [0, 79, 163, 380], "label": "background", "iou": 0.20263380868266484}, {"bbox": [0, 166, 56, 201], "label": "background", "iou": 0.0}, {"bbox": [136, 225, 186, 277], "label": "background", "iou": 0.05519388621568073}, {"bbox": [0, 0, 23, 21], "label": "background", "iou": 0.0}, {"bbox": [369, 36, 400, 67], "label": "background", "iou": 0.0}, {"bbox": [35, 47, 400, 400], "label": "background", "iou": 0.26916061934883}, {"bbox": [118, 294, 172, 328], "label": "background", "iou": 0.0}, {"bbox": [241, 289, 278, 321], "label": "background", "iou": 0.0}, {"bbox": [80, 69, 343, 275], "label": "pothole", "iou": 0.6401122226734098}, {"bbox": [251, 321, 317, 400], "label": "background", "iou": 0.0}, {"bbox": [0, 166, 57, 216], "label": "background", "iou": 0.0}, {"bbox": [0, 276, 27, 293], "label": "background", "iou": 0.0}, {"bbox": [114, 305, 134, 328], "label": "background", "iou": 0.0}, {"bbox": [0, 0, 164, 216], "label": "background", "iou": 0.17121090617481957}, {"bbox": [186, 183, 233, 221], "label": "background", "iou": 0.05149942329873126}, {"bbox": [159, 103, 285, 153], "label": "background", "iou": 0.17995968902965737}, {"bbox": [386, 92, 400, 134], "label": "background", "iou": 0.0}, {"bbox": [87, 70, 135, 109], "label": "background", "iou": 0.020093770931011386}, {"bbox": [118, 57, 140, 81], "label": "background", "iou": 0.0}, {"bbox": [124, 0, 171, 45], "label": "background", "iou": 0.0}, {"bbox": [320, 98, 364, 142], "label": "background", "iou": 0.10807686750469585}, {"bbox": [257, 146, 292, 171], "label": "background", "iou": 0.06994818652849741}, {"bbox": [110, 201, 132, 226], "label": "background", "iou": 0.015859284890426758}, {"bbox": [99, 305, 136, 335], "label": "background", "iou": 0.0}, {"bbox": [372, 27, 400, 70], "label": "background", "iou": 0.0}, {"bbox": [119, 169, 146, 186], "label": "background", "iou": 0.013235294117647059}, {"bbox": [255, 242, 400, 400], "label": "background", "iou": 0.011202416069672707}, {"bbox": [220, 141, 246, 158], "label": "background", "iou": 0.012745098039215686}, {"bbox": [195, 175, 245, 213], "label": "background", "iou": 0.05478662053056517}, {"bbox": [59, 133, 83, 155], "label": "background", "iou": 0.00187809458767287}, {"bbox": [193, 163, 248, 213], "label": "background", "iou": 0.07929642445213379}, {"bbox": [236, 242, 400, 400], "label": "background", "iou": 0.017737167428110722}, {"bbox": [376, 151, 400, 220], "label": "background", "iou": 0.0}, {"bbox": [108, 91, 142, 111], "label": "background", "iou": 0.016617790811339198}, {"bbox": [92, 77, 335, 224], "label": "pothole", "iou": 0.5492836865385885}, {"bbox": [82, 77, 336, 239], "label": "pothole", "iou": 0.6293781425931497}, {"bbox": [244, 132, 302, 172], "label": "background", "iou": 0.15223923308055515}, {"bbox": [101, 193, 135, 225], "label": "background", "iou": 0.03137254901960784}, {"bbox": [82, 202, 179, 311], "label": "background", "iou": 0.1532658834322995}, {"bbox": [245, 202, 364, 344], "label": "background", "iou": 0.049186330349877946}, {"bbox": [80, 76, 334, 239], "label": "pothole", "iou": 0.6361016730463206}, {"bbox": [350, 237, 374, 264], "label": "background", "iou": 0.0}, {"bbox": [87, 57, 159, 117], "label": "background", "iou": 0.04434447300771208}, {"bbox": [56, 83, 84, 105], "label": "background", "iou": 0.0012481561329853626}, {"bbox": [250, 328, 282, 374], "label": "background", "iou": 0.0}, {"bbox": [241, 286, 278, 321], "label": "background", "iou": 0.0}, {"bbox": [125, 197, 149, 220], "label": "background", "iou": 0.01591695501730104}, {"bbox": [288, 372, 306, 395], "label": "background", "iou": 0.0}, {"bbox": [372, 29, 400, 70], "label": "background", "iou": 0.0}, {"bbox": [207, 334, 267, 400], "label": "background", "iou": 0.0}, {"bbox": [173, 103, 292, 185], "label": "background", "iou": 0.25758433325786734}, {"bbox": [101, 88, 142, 111], "label": "background", "iou": 0.019956479413617362}, {"bbox": [115, 16, 159, 52], "label": "background", "iou": 0.0}, {"bbox": [335, 79, 387, 139], "label": "background", "iou": 0.013740982480247337}, {"bbox": [250, 331, 316, 400], "label": "background", "iou": 0.0}, {"bbox": [361, 77, 383, 113], "label": "background", "iou": 0.0}, {"bbox": [0, 162, 51, 196], "label": "background", "iou": 0.0}, {"bbox": [186, 184, 233, 221], "label": "background", "iou": 0.0501441753171857}, {"bbox": [0, 185, 29, 232], "label": "background", "iou": 0.0}, {"bbox": [205, 132, 300, 190], "label": "background", "iou": 0.12867894855088743}, {"bbox": [43, 0, 400, 155], "label": "background", "iou": 0.16042077580539119}, {"bbox": [48, 309, 115, 371], "label": "background", "iou": 0.0}, {"bbox": [87, 70, 141, 111], "label": "background", "iou": 0.02551701134089393}, {"bbox": [143, 255, 166, 289], "label": "background", "iou": 0.0058715075875762305}, {"bbox": [320, 25, 400, 220], "label": "background", "iou": 0.07818659658344283}, {"bbox": [378, 25, 400, 63], "label": "background", "iou": 0.0}, {"bbox": [0, 0, 163, 178], "label": "background", "iou": 0.1229152709706992}, {"bbox": [202, 132, 303, 185], "label": "background", "iou": 0.12178104071510634}, {"bbox": [302, 320, 329, 348], "label": "background", "iou": 0.0}, {"bbox": [207, 334, 274, 400], "label": "background", "iou": 0.0}, {"bbox": [340, 126, 369, 151], "label": "background", "iou": 0.0}, {"bbox": [146, 227, 178, 275], "label": "background", "iou": 0.033797670701073305}, {"bbox": [115, 27, 144, 51], "label": "background", "iou": 0.0}, {"bbox": [369, 38, 395, 65], "label": "background", "iou": 0.0}, {"bbox": [0, 0, 164, 191], "label": "background", "iou": 0.14083241150442477}, {"bbox": [122, 285, 182, 332], "label": "background", "iou": 0.0}, {"bbox": [195, 132, 303, 213], "label": "background", "iou": 0.19903917833181478}, {"bbox": [56, 115, 100, 155], "label": "background", "iou": 0.02244668911335578}, {"bbox": [146, 15, 185, 45], "label": "background", "iou": 0.0}, {"bbox": [0, 360, 51, 400], "label": "background", "iou": 0.0}, {"bbox": [75, 337, 115, 371], "label": "background", "iou": 0.0}, {"bbox": [38, 79, 112, 156], "label": "background", "iou": 0.05167474084492368}, {"bbox": [124, 226, 185, 318], "label": "background", "iou": 0.0610417654184442}, {"bbox": [0, 0, 24, 21], "label": "background", "iou": 0.0}, {"bbox": [327, 54, 400, 220], "label": "background", "iou": 0.053715837317749836}, {"bbox": [49, 309, 116, 380], "label": "background", "iou": 0.0}, {"bbox": [153, 226, 186, 261], "label": "background", "iou": 0.03330449826989619}, {"bbox": [143, 122, 274, 189], "label": "background", "iou": 0.2530853517877739}, {"bbox": [133, 0, 223, 47], "label": "background", "iou": 0.0}, {"bbox": [335, 67, 388, 120], "label": "background", "iou": 0.009692671394799054}, {"bbox": [24, 138, 43, 163], "label": "background", "iou": 0.0}, {"bbox": [124, 168, 152, 184], "label": "background", "iou": 0.012918108419838524}, {"bbox": [196, 362, 228, 400], "label": "background", "iou": 0.0}, {"bbox": [274, 132, 298, 149], "label": "background", "iou": 0.07116692830978545}, {"bbox": [76, 69, 347, 224], "label": "pothole", "iou": 0.5286554370577096}, {"bbox": [385, 178, 400, 219], "label": "background", "iou": 0.0}, {"bbox": [324, 138, 352, 167], "label": "background", "iou": 0.0611219195849546}, {"bbox": [86, 167, 114, 188], "label": "background", "iou": 0.016955017301038062}, {"bbox": [153, 224, 174, 247], "label": "background", "iou": 0.013927335640138408}, {"bbox": [76, 69, 347, 225], "label": "pothole", "iou": 0.5320114667940755}, {"bbox": [87, 164, 114, 188], "label": "background", "iou": 0.018685121107266434}, {"bbox": [0, 0, 400, 196], "label": "background", "iou": 0.22550719611583145}, {"bbox": [101, 93, 141, 111], "label": "background", "iou": 0.019585253456221197}, {"bbox": [87, 57, 140, 100], "label": "background", "iou": 0.008678802434431374}, {"bbox": [232, 154, 275, 190], "label": "background", "iou": 0.04463667820069204}, {"bbox": [76, 162, 120, 188], "label": "background", "iou": 0.029898804047838085}, {"bbox": [252, 269, 271, 304], "label": "background", "iou": 0.0}, {"bbox": [250, 331, 303, 400], "label": "background", "iou": 0.0}, {"bbox": [47, 115, 100, 155], "label": "background", "iou": 0.022222222222222223}, {"bbox": [193, 132, 298, 213], "label": "background", "iou": 0.20581336907354666}, {"bbox": [264, 132, 303, 163], "label": "background", "iou": 0.1487671686248552}, {"bbox": [0, 0, 400, 191], "label": "background", "iou": 0.21675502782281034}, {"bbox": [374, 92, 400, 220], "label": "background", "iou": 0.0}, {"bbox": [71, 57, 140, 135], "label": "background", "iou": 0.06542205201850966}, {"bbox": [123, 168, 152, 184], "label": "background", "iou": 0.013379469434832756}, {"bbox": [321, 171, 400, 342], "label": "background", "iou": 0.0}, {"bbox": [0, 185, 29, 201], "label": "background", "iou": 0.0}, {"bbox": [250, 331, 284, 387], "label": "background", "iou": 0.0}, {"bbox": [346, 194, 360, 223], "label": "background", "iou": 0.0}, {"bbox": [104, 305, 136, 335], "label": "background", "iou": 0.0}, {"bbox": [381, 242, 400, 265], "label": "background", "iou": 0.0}, {"bbox": [101, 92, 141, 111], "label": "background", "iou": 0.019562715765247412}, {"bbox": [87, 160, 113, 188], "label": "background", "iou": 0.0209919261822376}, {"bbox": [21, 323, 182, 400], "label": "background", "iou": 0.0}, {"bbox": [251, 331, 317, 400], "label": "background", "iou": 0.0}, {"bbox": [135, 95, 159, 117], "label": "background", "iou": 0.01522491349480969}, {"bbox": [261, 321, 282, 362], "label": "background", "iou": 0.0}, {"bbox": [80, 81, 335, 260], "label": "pothole", "iou": 0.7288693743139407}, {"bbox": [54, 117, 101, 155], "label": "background", "iou": 0.022372995402041046}, {"bbox": [0, 282, 27, 325], "label": "background", "iou": 0.0}, {"bbox": [15, 162, 51, 191], "label": "background", "iou": 0.0}, {"bbox": [61, 229, 116, 265], "label": "background", "iou": 0.03559322033898305}, {"bbox": [367, 100, 400, 223], "label": "background", "iou": 0.0}, {"bbox": [385, 92, 400, 124], "label": "background", "iou": 0.0}, {"bbox": [154, 262, 174, 285], "label": "background", "iou": 0.0011396011396011395}, {"bbox": [79, 333, 118, 354], "label": "background", "iou": 0.0}, {"bbox": [225, 154, 275, 190], "label": "background", "iou": 0.05190311418685121}, {"bbox": [39, 209, 84, 237], "label": "background", "iou": 0.0031260466674109637}, {"bbox": [0, 0, 162, 191], "label": "background", "iou": 0.13792744676423666}, {"bbox": [0, 360, 55, 400], "label": "background", "iou": 0.0}, {"bbox": [262, 333, 303, 400], "label": "background", "iou": 0.0}, {"bbox": [230, 133, 267, 160], "label": "background", "iou": 0.028806228373702423}, {"bbox": [54, 76, 141, 155], "label": "background", "iou": 0.09835588919433284}, {"bbox": [135, 95, 190, 117], "label": "background", "iou": 0.03489042675893887}, {"bbox": [138, 253, 158, 273], "label": "background", "iou": 0.006310958118187034}, {"bbox": [42, 218, 73, 237], "label": "background", "iou": 0.0}, {"bbox": [49, 46, 400, 400], "label": "background", "iou": 0.2791057028345164}, {"bbox": [192, 132, 303, 189], "label": "background", "iou": 0.14663199396023824}, {"bbox": [288, 69, 343, 117], "label": "background", "iou": 0.2859775764091537}, {"bbox": [225, 158, 275, 185], "label": "background", "iou": 0.03892733564013841}, {"bbox": [91, 81, 120, 113], "label": "background", "iou": 0.01571726046153407}, {"bbox": [159, 103, 285, 155], "label": "background", "iou": 0.18714729932051136}, {"bbox": [43, 71, 141, 155], "label": "background", "iou": 0.0949452680462351}, {"bbox": [205, 147, 244, 179], "label": "background", "iou": 0.035986159169550176}, {"bbox": [4, 358, 55, 400], "label": "background", "iou": 0.0}, {"bbox": [110, 201, 132, 225], "label": "background", "iou": 0.01522491349480969}, {"bbox": [261, 327, 284, 362], "label": "background", "iou": 0.0}, {"bbox": [0, 0, 400, 194], "label": "background", "iou": 0.2220287331301698}, {"bbox": [62, 329, 115, 371], "label": "background", "iou": 0.0}, {"bbox": [0, 176, 30, 216], "label": "background", "iou": 0.0}, {"bbox": [67, 202, 105, 224], "label": "background", "iou": 0.015729565863982154}, {"bbox": [327, 38, 400, 220], "label": "background", "iou": 0.05025125628140704}, {"bbox": [42, 335, 67, 354], "label": "background", "iou": 0.0}, {"bbox": [134, 95, 189, 120], "label": "background", "iou": 0.039648212226066896}, {"bbox": [0, 162, 51, 191], "label": "background", "iou": 0.0}, {"bbox": [232, 158, 274, 185], "label": "background", "iou": 0.032698961937716264}, {"bbox": [99, 206, 132, 224], "label": "background", "iou": 0.0171280276816609}, {"bbox": [0, 103, 160, 400], "label": "background", "iou": 0.18580496249278708}, {"bbox": [250, 331, 282, 374], "label": "background", "iou": 0.0}, {"bbox": [65, 330, 116, 380], "label": "background", "iou": 0.0}, {"bbox": [253, 331, 317, 400], "label": "background", "iou": 0.0}, {"bbox": [264, 129, 303, 171], "label": "background", "iou": 0.1923325784535749}, {"bbox": [303, 275, 333, 329], "label": "background", "iou": 0.0}, {"bbox": [95, 0, 223, 95], "label": "background", "iou": 0.002740195238910772}, {"bbox": [93, 319, 136, 346], "label": "background", "iou": 0.0}, {"bbox": [117, 137, 141, 158], "label": "background", "iou": 0.01453287197231834}, {"bbox": [0, 184, 203, 400], "label": "background", "iou": 0.143256464011181}, {"bbox": [320, 209, 361, 240], "label": "background", "iou": 0.0}, {"bbox": [138, 284, 168, 300], "label": "background", "iou": 0.0}, {"bbox": [274, 132, 300, 149], "label": "background", "iou": 0.07709750566893424}, {"bbox": [335, 77, 388, 122], "label": "background", "iou": 0.010707171314741035}, {"bbox": [54, 133, 83, 155], "label": "background", "iou": 0.0018722341994780439}, {"bbox": [123, 145, 164, 184], "label": "background", "iou": 0.04610726643598616}, {"bbox": [54, 115, 107, 155], "label": "background", "iou": 0.030235162374020158}, {"bbox": [20, 261, 45, 293], "label": "background", "iou": 0.0}, {"bbox": [257, 153, 284, 172], "label": "background", "iou": 0.027978933508887426}, {"bbox": [346, 79, 367, 105], "label": "background", "iou": 0.0}, {"bbox": [61, 229, 116, 264], "label": "background", "iou": 0.035648606592162964}, {"bbox": [67, 77, 336, 281], "label": "pothole", "iou": 0.6319702602230484}, {"bbox": [99, 305, 137, 335], "label": "background", "iou": 0.0}, {"bbox": [61, 230, 106, 257], "label": "background", "iou": 0.01994714858068366}, {"bbox": [118, 98, 314, 221], "label": "pothole", "iou": 0.5321344800625488}, {"bbox": [36, 218, 63, 237], "label": "background", "iou": 0.0}, {"bbox": [0, 0, 91, 99], "label": "background", "iou": 0.001260484942934409}, {"bbox": [276, 202, 312, 236], "label": "background", "iou": 0.007633587786259542}, {"bbox": [350, 233, 374, 264], "label": "background", "iou": 0.0}, {"bbox": [39, 209, 85, 237], "label": "background", "iou": 0.003907558334263705}, {"bbox": [283, 47, 343, 117], "label": "background", "iou": 0.26037304910544345}, {"bbox": [335, 77, 383, 128], "label": "background", "iou": 0.012124211307682792}, {"bbox": [262, 98, 311, 148], "label": "background", "iou": 0.292120637928312}, {"bbox": [118, 69, 344, 171], "label": "background", "iou": 0.2843604004449388}, {"bbox": [208, 142, 234, 160], "label": "background", "iou": 0.013494809688581315}, {"bbox": [114, 305, 134, 332], "label": "background", "iou": 0.0}, {"bbox": [137, 145, 164, 171], "label": "background", "iou": 0.020242214532871974}, {"bbox": [381, 36, 400, 70], "label": "background", "iou": 0.0}, {"bbox": [119, 95, 211, 168], "label": "background", "iou": 0.19365628604382928}, {"bbox": [124, 0, 223, 45], "label": "background", "iou": 0.0}, {"bbox": [76, 69, 347, 281], "label": "pothole", "iou": 0.6036343382301748}, {"bbox": [301, 319, 328, 356], "label": "background", "iou": 0.0}, {"bbox": [375, 151, 400, 200], "label": "background", "iou": 0.0}, {"bbox": [250, 328, 284, 374], "label": "background", "iou": 0.0}, {"bbox": [143, 122, 303, 189], "label": "background", "iou": 0.26275971407114845}, {"bbox": [382, 37, 400, 70], "label": "background", "iou": 0.0}, {"bbox": [385, 92, 400, 138], "label": "background", "iou": 0.0}, {"bbox": [0, 372, 36, 400], "label": "background", "iou": 0.0}, {"bbox": [155, 230, 203, 345], "label": "background", "iou": 0.042314872433105166}, {"bbox": [0, 319, 182, 400], "label": "background", "iou": 0.0}, {"bbox": [202, 190, 233, 205], "label": "background", "iou": 0.013408304498269897}, {"bbox": [26, 96, 160, 213], "label": "background", "iou": 0.22830381969852187}, {"bbox": [131, 227, 186, 281], "label": "background", "iou": 0.05713884599185736}, {"bbox": [221, 76, 288, 117], "label": "background", "iou": 0.0669350780070458}, {"bbox": [124, 0, 169, 45], "label": "background", "iou": 0.0}, {"bbox": [123, 168, 148, 184], "label": "background", "iou": 0.011534025374855825}, {"bbox": [98, 89, 120, 113], "label": "background", "iou": 0.012014946823799942}, {"bbox": [131, 219, 188, 281], "label": "background", "iou": 0.07195152739207271}, {"bbox": [195, 186, 231, 212], "label": "background", "iou": 0.02698961937716263}, {"bbox": [202, 357, 218, 385], "label": "background", "iou": 0.0}, {"bbox": [52, 309, 136, 371], "label": "background", "iou": 0.0}, {"bbox": [11, 355, 55, 388], "label": "background", "iou": 0.0}, {"bbox": [183, 184, 233, 217], "label": "background", "iou": 0.04757785467128028}, {"bbox": [36, 209, 84, 239], "label": "background", "iou": 0.0033333333333333335}, {"bbox": [376, 180, 400, 220], "label": "background", "iou": 0.0}, {"bbox": [302, 320, 371, 400], "label": "background", "iou": 0.0}, {"bbox": [42, 210, 77, 237], "label": "background", "iou": 0.0}, {"bbox": [24, 142, 45, 163], "label": "background", "iou": 0.0}, {"bbox": [105, 305, 136, 335], "label": "background", "iou": 0.0}, {"bbox": [24, 360, 51, 387], "label": "background", "iou": 0.0}, {"bbox": [262, 98, 311, 138], "label": "background", "iou": 0.23821020441010785}, {"bbox": [136, 225, 184, 274], "label": "background", "iou": 0.05324232081911263}, {"bbox": [220, 141, 247, 158], "label": "background", "iou": 0.013235294117647059}, {"bbox": [137, 145, 158, 171], "label": "background", "iou": 0.0157439446366782}, {"bbox": [221, 68, 321, 117], "label": "background", "iou": 0.20187634226291398}, {"bbox": [320, 79, 386, 167], "label": "background", "iou": 0.14892981582877055}, {"bbox": [76, 162, 115, 193], "label": "background", "iou": 0.031174577634754626}, {"bbox": [76, 76, 334, 239], "label": "pothole", "iou": 0.6273062730627307}, {"bbox": [303, 320, 329, 347], "label": "background", "iou": 0.0}, {"bbox": [106, 0, 400, 114], "label": "background", "iou": 0.05952380952380952}, {"bbox": [369, 25, 400, 66], "label": "background", "iou": 0.0}, {"bbox": [99, 311, 137, 335], "label": "background", "iou": 0.0}, {"bbox": [54, 57, 159, 155], "label": "background", "iou": 0.12002191726233469}, {"bbox": [252, 289, 278, 305], "label": "background", "iou": 0.0}, {"bbox": [118, 56, 140, 78], "label": "background", "iou": 0.0}, {"bbox": [146, 0, 223, 46], "label": "background", "iou": 0.0}, {"bbox": [164, 9, 191, 26], "label": "background", "iou": 0.0}, {"bbox": [124, 0, 223, 46], "label": "background", "iou": 0.0}, {"bbox": [0, 323, 182, 400], "label": "background", "iou": 0.0}, {"bbox": [24, 360, 51, 380], "label": "background", "iou": 0.0}, {"bbox": [27, 359, 55, 388], "label": "background", "iou": 0.0}, {"bbox": [153, 224, 186, 261], "label": "background", "iou": 0.0352076124567474}, {"bbox": [250, 321, 325, 400], "label": "background", "iou": 0.0}, {"bbox": [0, 166, 51, 196], "label": "background", "iou": 0.0}, {"bbox": [0, 194, 19, 216], "label": "background", "iou": 0.0}, {"bbox": [0, 183, 29, 216], "label": "background", "iou": 0.0}, {"bbox": [195, 124, 300, 221], "label": "background", "iou": 0.23827003753587989}, {"bbox": [82, 202, 179, 272], "label": "background", "iou": 0.1696186823104693}, {"bbox": [381, 242, 400, 266], "label": "background", "iou": 0.0}, {"bbox": [131, 252, 175, 281], "label": "background", "iou": 0.014903466184938466}, {"bbox": [275, 82, 301, 111], "label": "background", "iou": 0.13151927437641722}, {"bbox": [87, 57, 141, 111], "label": "background", "iou": 0.025028627515131685}, {"bbox": [122, 294, 182, 332], "label": "background", "iou": 0.0}, {"bbox": [225, 132, 298, 185], "label": "background", "iou": 0.1049482163406214}, {"bbox": [0, 359, 55, 400], "label": "background", "iou": 0.0}, {"bbox": [61, 329, 88, 348], "label": "background", "iou": 0.0}, {"bbox": [274, 82, 301, 111], "label": "background", "iou": 0.13657770800627944}, {"bbox": [153, 179, 223, 263], "label": "background", "iou": 0.1695501730103806}, {"bbox": [0, 280, 31, 323], "label": "background", "iou": 0.0}, {"bbox": [320, 25, 400, 342], "label": "background", "iou": 0.0523590333716916}, {"bbox": [135, 96, 159, 117], "label": "background", "iou": 0.01453287197231834}, {"bbox": [195, 186, 230, 212], "label": "background", "iou": 0.026239907727797}, {"bbox": [261, 321, 281, 362], "label": "background", "iou": 0.0}, {"bbox": [122, 0, 400, 117], "label": "background", "iou": 0.06675031367628607}, {"bbox": [96, 0, 400, 113], "label": "background", "iou": 0.05645310070368711}, {"bbox": [335, 78, 388, 115], "label": "background", "iou": 0.009446339543426921}, {"bbox": [0, 71, 163, 371], "label": "background", "iou": 0.20310925579386785}, {"bbox": [153, 225, 203, 345], "label": "background", "iou": 0.05034856700232378}, {"bbox": [0, 182, 29, 201], "label": "background", "iou": 0.0}, {"bbox": [251, 331, 325, 400], "label": "background", "iou": 0.0}, {"bbox": [250, 340, 282, 373], "label": "background", "iou": 0.0}, {"bbox": [303, 275, 344, 369], "label": "background", "iou": 0.0}, {"bbox": [124, 0, 185, 45], "label": "background", "iou": 0.0}, {"bbox": [379, 25, 400, 67], "label": "background", "iou": 0.0}, {"bbox": [122, 135, 151, 150], "label": "background", "iou": 0.012543252595155709}, {"bbox": [66, 305, 136, 380], "label": "background", "iou": 0.0}, {"bbox": [135, 97, 159, 114], "label": "background", "iou": 0.011764705882352941}, {"bbox": [116, 136, 145, 151], "label": "background", "iou": 0.012543252595155709}, {"bbox": [199, 124, 292, 185], "label": "background", "iou": 0.14743516833484988}, {"bbox": [0, 71, 168, 371], "label": "background", "iou": 0.21334854535082715}, {"bbox": [155, 0, 224, 21], "label": "background", "iou": 0.0}, {"bbox": [320, 194, 361, 240], "label": "background", "iou": 0.0}, {"bbox": [250, 326, 282, 373], "label": "background", "iou": 0.0}, {"bbox": [43, 71, 135, 155], "label": "background", "iou": 0.08590889304278801}, {"bbox": [80, 81, 335, 281], "label": "pothole", "iou": 0.68}, {"bbox": [192, 122, 303, 189], "label": "background", "iou": 0.1714460545712458}, {"bbox": [249, 142, 292, 165], "label": "background", "iou": 0.06563094483195941}, {"bbox": [205, 144, 244, 182], "label": "background", "iou": 0.04273356401384083}, {"bbox": [268, 146, 292, 171], "label": "background", "iou": 0.07320793085917641}, {"bbox": [248, 309, 282, 373], "label": "background", "iou": 0.0}, {"bbox": [0, 0, 223, 178], "label": "background", "iou": 0.19261729899618357}, {"bbox": [49, 0, 400, 400], "label": "background", "iou": 0.24700854700854702}, {"bbox": [236, 321, 293, 380], "label": "background", "iou": 0.0}, {"bbox": [277, 70, 304, 104], "label": "background", "iou": 0.11295180722891567}, {"bbox": [264, 134, 300, 163], "label": "background", "iou": 0.12518678399468702}, {"bbox": [201, 142, 247, 185], "label": "background", "iou": 0.057035755478662055}, {"bbox": [59, 330, 88, 350], "label": "background", "iou": 0.0}, {"bbox": [290, 321, 322, 368], "label": "background", "iou": 0.0}, {"bbox": [315, 58, 400, 223], "label": "background", "iou": 0.1127506195088984}, {"bbox": [64, 309, 91, 337], "label": "background", "iou": 0.0}, {"bbox": [0, 362, 18, 400], "label": "background", "iou": 0.0}, {"bbox": [202, 142, 247, 184], "label": "background", "iou": 0.054498269896193774}, {"bbox": [280, 70, 317, 104], "label": "background", "iou": 0.15248928453676228}, {"bbox": [155, 81, 400, 400], "label": "background", "iou": 0.24124085583851274}, {"bbox": [260, 146, 292, 171], "label": "background", "iou": 0.070808064251762}, {"bbox": [201, 186, 234, 199], "label": "background", "iou": 0.012370242214532872}, {"bbox": [248, 275, 340, 400], "label": "background", "iou": 0.0}, {"bbox": [87, 76, 142, 111], "label": "background", "iou": 0.02621250350434539}, {"bbox": [186, 184, 233, 198], "label": "background", "iou": 0.018973471741637833}, {"bbox": [193, 152, 274, 221], "label": "background", "iou": 0.161159169550173}, {"bbox": [225, 153, 275, 185], "label": "background", "iou": 0.0461361014994233}, {"bbox": [131, 253, 158, 281], "label": "background", "iou": 0.008452147186886366}, {"bbox": [26, 79, 160, 213], "label": "background", "iou": 0.2207997031264496}, {"bbox": [261, 331, 281, 362], "label": "background", "iou": 0.0}, {"bbox": [76, 163, 114, 193], "label": "background", "iou": 0.029310344827586206}, {"bbox": [303, 321, 325, 369], "label": "background", "iou": 0.0}, {"bbox": [0, 5, 91, 99], "label": "background", "iou": 0.0012737673406053869}, {"bbox": [99, 205, 132, 224], "label": "background", "iou": 0.018079584775086505}, {"bbox": [96, 0, 400, 117], "label": "background", "iou": 0.06559068017717372}, {"bbox": [220, 176, 264, 210], "label": "background", "iou": 0.043137254901960784}, {"bbox": [245, 218, 364, 344], "label": "background", "iou": 0.03746867167919799}, {"bbox": [251, 76, 335, 148], "label": "pothole", "iou": 0.555863708399366}, {"bbox": [124, 155, 157, 184], "label": "background", "iou": 0.02759515570934256}, {"bbox": [136, 225, 184, 277], "label": "background", "iou": 0.05302515295717199}, {"bbox": [250, 357, 274, 397], "label": "background", "iou": 0.0}, {"bbox": [293, 298, 400, 400], "label": "background", "iou": 0.0}, {"bbox": [59, 330, 115, 371], "label": "background", "iou": 0.0}, {"bbox": [230, 202, 374, 344], "label": "background", "iou": 0.06465816917728853}, {"bbox": [122, 285, 172, 332], "label": "background", "iou": 0.0}, {"bbox": [86, 202, 132, 224], "label": "background", "iou": 0.029181084198385235}, {"bbox": [42, 202, 185, 371], "label": "background", "iou": 0.12438618950264631}, {"bbox": [367, 297, 400, 400], "label": "background", "iou": 0.0}, {"bbox": [250, 339, 282, 373], "label": "background", "iou": 0.0}, {"bbox": [0, 276, 27, 323], "label": "background", "iou": 0.0}, {"bbox": [127, 285, 164, 311], "label": "background", "iou": 0.0}, {"bbox": [245, 218, 374, 344], "label": "background", "iou": 0.03650793650793651}, {"bbox": [225, 134, 300, 185], "label": "background", "iou": 0.10855949895615867}, {"bbox": [372, 27, 400, 67], "label": "background", "iou": 0.0}, {"bbox": [251, 321, 325, 400], "label": "background", "iou": 0.0}, {"bbox": [221, 47, 339, 117], "label": "background", "iou": 0.2063971031985516}, {"bbox": [253, 331, 325, 400], "label": "background", "iou": 0.0}, {"bbox": [230, 293, 263, 321], "label": "background", "iou": 0.0}, {"bbox": [196, 190, 233, 212], "label": "background", "iou": 0.023471741637831604}, {"bbox": [134, 95, 285, 155], "label": "background", "iou": 0.25906735751295334}, {"bbox": [369, 25, 400, 67], "label": "background", "iou": 0.0}, {"bbox": [286, 275, 343, 400], "label": "background", "iou": 0.0}, {"bbox": [225, 173, 251, 193], "label": "background", "iou": 0.014994232987312572}, {"bbox": [0, 197, 23, 215], "label": "background", "iou": 0.0}, {"bbox": [201, 186, 233, 205], "label": "background", "iou": 0.017531718569780853}, {"bbox": [133, 6, 179, 47], "label": "background", "iou": 0.0}, {"bbox": [268, 132, 298, 170], "label": "background", "iou": 0.15299446401610467}, {"bbox": [123, 153, 159, 184], "label": "background", "iou": 0.03217993079584775}, {"bbox": [197, 373, 237, 400], "label": "background", "iou": 0.0}, {"bbox": [236, 233, 400, 400], "label": "background", "iou": 0.024562561901617697}, {"bbox": [20, 261, 45, 280], "label": "background", "iou": 0.0}, {"bbox": [220, 177, 264, 210], "label": "background", "iou": 0.04186851211072665}, {"bbox": [68, 200, 88, 226], "label": "background", "iou": 0.00594421582075903}, {"bbox": [59, 118, 101, 155], "label": "background", "iou": 0.021913867501480666}, {"bbox": [201, 142, 250, 190], "label": "background", "iou": 0.06782006920415225}, {"bbox": [313, 275, 344, 331], "label": "background", "iou": 0.0}, {"bbox": [124, 0, 185, 46], "label": "background", "iou": 0.0}, {"bbox": [0, 0, 75, 31], "label": "background", "iou": 0.0}, {"bbox": [372, 25, 400, 67], "label": "background", "iou": 0.0}, {"bbox": [326, 33, 400, 175], "label": "background", "iou": 0.06568241469816273}, {"bbox": [82, 202, 179, 289], "label": "background", "iou": 0.16208058213178816}, {"bbox": [207, 333, 303, 400], "label": "background", "iou": 0.0}, {"bbox": [0, 162, 51, 232], "label": "background", "iou": 0.0}, {"bbox": [27, 360, 55, 388], "label": "background", "iou": 0.0}, {"bbox": [346, 79, 386, 112], "label": "background", "iou": 0.0}, {"bbox": [153, 177, 264, 263], "label": "background", "iou": 0.27525951557093425}, {"bbox": [22, 0, 400, 400], "label": "background", "iou": 0.22936507936507936}, {"bbox": [218, 143, 246, 160], "label": "background", "iou": 0.013725490196078431}, {"bbox": [327, 54, 400, 135], "label": "background", "iou": 0.050514162006133866}, {"bbox": [303, 275, 344, 347], "label": "background", "iou": 0.0}, {"bbox": [62, 309, 115, 371], "label": "background", "iou": 0.0}, {"bbox": [286, 353, 322, 400], "label": "background", "iou": 0.0}, {"bbox": [302, 310, 371, 400], "label": "background", "iou": 0.0}, {"bbox": [201, 186, 225, 205], "label": "background", "iou": 0.01314878892733564}, {"bbox": [296, 275, 347, 347], "label": "background", "iou": 0.0}, {"bbox": [195, 158, 274, 213], "label": "background", "iou": 0.1252883506343714}, {"bbox": [82, 125, 224, 278], "label": "pothole", "iou": 0.5382895167448456}, {"bbox": [203, 140, 244, 182], "label": "background", "iou": 0.04965397923875432}, {"bbox": [67, 319, 137, 371], "label": "background", "iou": 0.0}, {"bbox": [355, 237, 374, 264], "label": "background", "iou": 0.0}, {"bbox": [0, 198, 23, 232], "label": "background", "iou": 0.0}, {"bbox": [0, 305, 136, 400], "label": "background", "iou": 0.0}, {"bbox": [185, 334, 274, 400], "label": "background", "iou": 0.0}, {"bbox": [255, 233, 400, 400], "label": "background", "iou": 0.015501069039244086}, {"bbox": [283, 68, 321, 100], "label": "background", "iou": 0.12973500243862787}, {"bbox": [0, 166, 51, 216], "label": "background", "iou": 0.0}, {"bbox": [143, 125, 303, 189], "label": "background", "iou": 0.25139291285937154}, {"bbox": [138, 226, 185, 278], "label": "background", "iou": 0.05054049465164978}, {"bbox": [133, 6, 191, 47], "label": "background", "iou": 0.0}, {"bbox": [134, 70, 335, 153], "label": "background", "iou": 0.25215059769858117}, {"bbox": [315, 36, 400, 223], "label": "background", "iou": 0.10200754101701824}, {"bbox": [119, 69, 343, 168], "label": "background", "iou": 0.27348474667383416}, {"bbox": [232, 146, 292, 190], "label": "background", "iou": 0.06531171500342543}, {"bbox": [252, 286, 278, 305], "label": "background", "iou": 0.0}, {"bbox": [119, 46, 356, 184], "label": "background", "iou": 0.28266331658291455}, {"bbox": [61, 329, 115, 371], "label": "background", "iou": 0.0}, {"bbox": [0, 0, 164, 369], "label": "background", "iou": 0.1764793118789856}, {"bbox": [138, 253, 166, 289], "label": "background", "iou": 0.008705483323911814}, {"bbox": [225, 142, 292, 185], "label": "background", "iou": 0.07243604385564184}, {"bbox": [261, 275, 400, 400], "label": "background", "iou": 0.0}, {"bbox": [0, 0, 163, 216], "label": "background", "iou": 0.1694387738027509}, {"bbox": [193, 134, 300, 221], "label": "background", "iou": 0.2194777112441783}, {"bbox": [24, 76, 160, 213], "label": "background", "iou": 0.21739130434782608}, {"bbox": [384, 36, 400, 67], "label": "background", "iou": 0.0}, {"bbox": [42, 331, 77, 354], "label": "background", "iou": 0.0}, {"bbox": [230, 269, 271, 321], "label": "background", "iou": 0.0}, {"bbox": [134, 95, 285, 153], "label": "background", "iou": 0.2504461972479705}, {"bbox": [146, 227, 186, 275], "label": "background", "iou": 0.04214123006833713}, {"bbox": [263, 132, 303, 163], "label": "background", "iou": 0.14800790253539678}, {"bbox": [93, 305, 136, 346], "label": "background", "iou": 0.0}, {"bbox": [232, 134, 300, 190], "label": "background", "iou": 0.10877396862289367}, {"bbox": [195, 121, 273, 221], "label": "background", "iou": 0.22491349480968859}, {"bbox": [62, 319, 136, 371], "label": "background", "iou": 0.0}, {"bbox": [52, 309, 115, 371], "label": "background", "iou": 0.0}, {"bbox": [251, 275, 333, 400], "label": "background", "iou": 0.0}, {"bbox": [0, 79, 160, 232], "label": "background", "iou": 0.22942643391521197}, {"bbox": [302, 171, 400, 400], "label": "background", "iou": 0.0}, {"bbox": [251, 25, 400, 137], "label": "background", "iou": 0.1947034688549049}, {"bbox": [87, 162, 113, 188], "label": "background", "iou": 0.019492502883506343}, {"bbox": [199, 124, 267, 160], "label": "background", "iou": 0.07058823529411765}, {"bbox": [218, 47, 339, 119], "label": "background", "iou": 0.21132075471698114}, {"bbox": [250, 331, 281, 397], "label": "background", "iou": 0.0}, {"bbox": [320, 79, 367, 142], "label": "background", "iou": 0.14049586776859505}, {"bbox": [54, 98, 112, 155], "label": "background", "iou": 0.05043968807035009}, {"bbox": [303, 275, 343, 331], "label": "background", "iou": 0.0}, {"bbox": [218, 76, 288, 119], "label": "background", "iou": 0.06843455945252352}, {"bbox": [248, 275, 400, 400], "label": "background", "iou": 0.0}, {"bbox": [264, 134, 300, 170], "label": "background", "iou": 0.1536189069423929}, {"bbox": [0, 46, 400, 400], "label": "background", "iou": 0.24491525423728813}, {"bbox": [0, 358, 55, 400], "label": "background", "iou": 0.0}, {"bbox": [218, 25, 400, 220], "label": "background", "iou": 0.16153846153846155}, {"bbox": [288, 275, 343, 368], "label": "background", "iou": 0.0}, {"bbox": [195, 144, 274, 213], "label": "background", "iou": 0.15717993079584774}, {"bbox": [201, 122, 302, 190], "label": "background", "iou": 0.1571969696969697}, {"bbox": [245, 171, 400, 344], "label": "background", "iou": 0.06267712725513237}, {"bbox": [0, 184, 182, 400], "label": "background", "iou": 0.12395187750637987}, {"bbox": [99, 285, 182, 335], "label": "background", "iou": 0.0}, {"bbox": [261, 327, 325, 400], "label": "background", "iou": 0.0}, {"bbox": [218, 76, 311, 148], "label": "background", "iou": 0.258505467800729}, {"bbox": [230, 202, 364, 344], "label": "background", "iou": 0.0664813343923749}, {"bbox": [0, 79, 182, 380], "label": "background", "iou": 0.24042594492665206}, {"bbox": [185, 373, 237, 400], "label": "background", "iou": 0.0}, {"bbox": [95, 0, 400, 117], "label": "background", "iou": 0.06584567845133145}, {"bbox": [0, 355, 55, 400], "label": "background", "iou": 0.0}, {"bbox": [201, 142, 274, 185], "label": "background", "iou": 0.09051326412918108}, {"bbox": [252, 242, 400, 400], "label": "background", "iou": 0.012273361227336122}, {"bbox": [67, 77, 336, 239], "label": "pothole", "iou": 0.607666707752989}, {"bbox": [320, 33, 400, 175], "label": "background", "iou": 0.09951112826450534}, {"bbox": [320, 79, 367, 167], "label": "background", "iou": 0.1786695330228114}, {"bbox": [71, 57, 159, 135], "label": "background", "iou": 0.08455815167732672}, {"bbox": [185, 275, 343, 400], "label": "background", "iou": 0.0}, {"bbox": [80, 69, 343, 285], "label": "pothole", "iou": 0.6104773975496409}, {"bbox": [0, 162, 51, 216], "label": "background", "iou": 0.0}, {"bbox": [250, 275, 347, 400], "label": "background", "iou": 0.0}, {"bbox": [288, 327, 325, 368], "label": "background", "iou": 0.0}, {"bbox": [82, 76, 335, 278], "label": "pothole", "iou": 0.66749601523928}, {"bbox": [0, 0, 400, 216], "label": "background", "iou": 0.2587325349301397}, {"bbox": [48, 330, 115, 371], "label": "background", "iou": 0.0}, {"bbox": [82, 95, 300, 278], "label": "pothole", "iou": 0.8442477000692452}, {"bbox": [193, 158, 275, 213], "label": "background", "iou": 0.13004613610149943}, {"bbox": [327, 25, 400, 220], "label": "background", "iou": 0.047748976807639835}, {"bbox": [118, 230, 203, 345], "label": "background", "iou": 0.06952965235173825}, {"bbox": [201, 132, 302, 185], "label": "background", "iou": 0.12344951450861537}, {"bbox": [205, 133, 267, 179], "label": "background", "iou": 0.08223760092272203}, {"bbox": [250, 275, 344, 400], "label": "background", "iou": 0.0}, {"bbox": [372, 25, 400, 70], "label": "background", "iou": 0.0}, {"bbox": [118, 225, 185, 328], "label": "background", "iou": 0.0670550195031821}, {"bbox": [203, 140, 274, 185], "label": "background", "iou": 0.0921280276816609}, {"bbox": [54, 93, 159, 155], "label": "background", "iou": 0.13249566962690054}, {"bbox": [95, 0, 400, 113], "label": "background", "iou": 0.056285474038259405}, {"bbox": [262, 69, 343, 148], "label": "pothole", "iou": 0.5583815028901734}, {"bbox": [42, 319, 137, 354], "label": "background", "iou": 0.0}, {"bbox": [0, 0, 179, 380], "label": "background", "iou": 0.19599394433445907}, {"bbox": [195, 144, 245, 213], "label": "background", "iou": 0.09948096885813149}, {"bbox": [134, 25, 400, 221], "label": "background", "iou": 0.28111442316205765}, {"bbox": [48, 305, 136, 371], "label": "background", "iou": 0.0}, {"bbox": [286, 327, 325, 400], "label": "background", "iou": 0.0}, {"bbox": [250, 326, 317, 400], "label": "background", "iou": 0.0}, {"bbox": [244, 132, 303, 165], "label": "background", "iou": 0.142347166443552}, {"bbox": [0, 57, 165, 375], "label": "background", "iou": 0.19876203576341128}, {"bbox": [261, 331, 303, 400], "label": "background", "iou": 0.0}, {"bbox": [52, 321, 115, 371], "label": "background", "iou": 0.0}, {"bbox": [61, 317, 136, 380], "label": "background", "iou": 0.0}, {"bbox": [35, 0, 400, 400], "label": "background", "iou": 0.23753424657534247}, {"bbox": [369, 25, 400, 65], "label": "background", "iou": 0.0}, {"bbox": [82, 77, 336, 281], "label": "pothole", "iou": 0.6584093872229465}, {"bbox": [293, 286, 400, 400], "label": "background", "iou": 0.0}, {"bbox": [192, 122, 274, 189], "label": "background", "iou": 0.15841983852364475}, {"bbox": [185, 334, 267, 400], "label": "background", "iou": 0.0}, {"bbox": [0, 0, 182, 380], "label": "background", "iou": 0.20046242774566475}, {"bbox": [0, 0, 223, 191], "label": "background", "iou": 0.21877858742626416}, {"bbox": [302, 297, 400, 400], "label": "background", "iou": 0.0}, {"bbox": [205, 147, 244, 184], "label": "background", "iou": 0.04160899653979239}, {"bbox": [0, 0, 223, 216], "label": "background", "iou": 0.2667502522858628}, {"bbox": [249, 134, 300, 165], "label": "background", "iou": 0.12384757221880763}, {"bbox": [76, 70, 334, 239], "label": "pothole", "iou": 0.6073672539115437}, {"bbox": [230, 218, 364, 344], "label": "background", "iou": 0.05061124694376528}, {"bbox": [0, 0, 163, 371], "label": "background", "iou": 0.17410510469750626}, {"bbox": [315, 25, 400, 223], "label": "background", "iou": 0.09736880501921112}, {"bbox": [0, 57, 165, 400], "label": "background", "iou": 0.1880898145135047}, {"bbox": [0, 0, 400, 224], "label": "background", "iou": 0.2712765957446808}, {"bbox": [250, 275, 343, 400], "label": "background", "iou": 0.0}, {"bbox": [202, 142, 274, 185], "label": "background", "iou": 0.08927335640138408}, {"bbox": [52, 200, 88, 226], "label": "background", "iou": 0.00587437867148667}, {"bbox": [201, 122, 250, 190], "label": "background", "iou": 0.09607843137254903}, {"bbox": [250, 331, 325, 400], "label": "background", "iou": 0.0}, {"bbox": [286, 327, 323, 400], "label": "background", "iou": 0.0}, {"bbox": [205, 147, 292, 185], "label": "background", "iou": 0.08581065630002287}, {"bbox": [61, 305, 136, 380], "label": "background", "iou": 0.0}, {"bbox": [203, 132, 303, 185], "label": "background", "iou": 0.1202959060722392}, {"bbox": [63, 57, 159, 145], "label": "background", "iou": 0.10304611371134811}, {"bbox": [146, 0, 223, 45], "label": "background", "iou": 0.0}, {"bbox": [0, 0, 164, 371], "label": "background", "iou": 0.1757668258579095}, {"bbox": [245, 202, 374, 344], "label": "background", "iou": 0.047805456702253855}, {"bbox": [42, 200, 88, 237], "label": "background", "iou": 0.008202627057584658}, {"bbox": [87, 76, 123, 108], "label": "background", "iou": 0.014266304347826086}, {"bbox": [0, 0, 168, 400], "label": "background", "iou": 0.17211228716060745}, {"bbox": [62, 309, 136, 371], "label": "background", "iou": 0.0}, {"bbox": [0, 70, 163, 400], "label": "background", "iou": 0.18975255513717051}, {"bbox": [76, 76, 334, 281], "label": "pothole", "iou": 0.655700510493477}, {"bbox": [302, 275, 371, 400], "label": "background", "iou": 0.0}, {"bbox": [0, 76, 160, 232], "label": "background", "iou": 0.2271604938271605}, {"bbox": [283, 47, 339, 100], "label": "background", "iou": 0.1498612395929695}, {"bbox": [199, 124, 276, 185], "label": "background", "iou": 0.13543829296424453}, {"bbox": [196, 176, 264, 212], "label": "background", "iou": 0.07058823529411765}, {"bbox": [185, 275, 400, 400], "label": "background", "iou": 0.0}, {"bbox": [221, 33, 400, 175], "label": "background", "iou": 0.2255488236682666}, {"bbox": [207, 333, 322, 400], "label": "background", "iou": 0.0}, {"bbox": [262, 327, 323, 400], "label": "background", "iou": 0.0}, {"bbox": [52, 319, 136, 371], "label": "background", "iou": 0.0}, {"bbox": [24, 0, 223, 162], "label": "background", "iou": 0.17001783403853551}, {"bbox": [195, 140, 245, 213], "label": "background", "iou": 0.1052479815455594}, {"bbox": [326, 25, 400, 175], "label": "background", "iou": 0.06322637695805963}, {"bbox": [48, 319, 136, 371], "label": "background", "iou": 0.0}, {"bbox": [163, 177, 264, 239], "label": "background", "iou": 0.18056516724336794}, {"bbox": [185, 327, 323, 400], "label": "background", "iou": 0.0}, {"bbox": [127, 253, 166, 311], "label": "background", "iou": 0.0117492399967135}, {"bbox": [82, 202, 185, 289], "label": "background", "iou": 0.17141323312307072}, {"bbox": [0, 70, 400, 400], "label": "background", "iou": 0.26272727272727275}, {"bbox": [0, 70, 163, 380], "label": "background", "iou": 0.19845288326300983}, {"bbox": [119, 95, 292, 239], "label": "pothole", "iou": 0.6630944407233758}, {"bbox": [0, 70, 182, 400], "label": "background", "iou": 0.224031007751938}, {"bbox": [320, 25, 400, 175], "label": "background", "iou": 0.09557642407018412}, {"bbox": [225, 149, 292, 185], "label": "background", "iou": 0.060741249142072753}, {"bbox": [196, 186, 233, 212], "label": "background", "iou": 0.027739331026528258}, {"bbox": [62, 319, 137, 371], "label": "background", "iou": 0.0}, {"bbox": [185, 202, 400, 400], "label": "background", "iou": 0.08631454606817415}, {"bbox": [82, 202, 203, 345], "label": "background", "iou": 0.16865628020952766}, {"bbox": [185, 333, 322, 400], "label": "background", "iou": 0.0}, {"bbox": [115, 0, 223, 52], "label": "background", "iou": 0.0}, {"bbox": [0, 71, 168, 400], "label": "background", "iou": 0.19948794538084064}, {"bbox": [163, 176, 264, 239], "label": "background", "iou": 0.18347750865051904}, {"bbox": [232, 132, 303, 185], "label": "background", "iou": 0.13128425065522992}, {"bbox": [244, 134, 300, 165], "label": "background", "iou": 0.1209665315923758}, {"bbox": [185, 331, 322, 400], "label": "background", "iou": 0.0}, {"bbox": [0, 96, 160, 232], "label": "background", "iou": 0.23880597014925373}, {"bbox": [0, 46, 356, 400], "label": "background", "iou": 0.27518567891830126}, {"bbox": [134, 95, 300, 221], "label": "pothole", "iou": 0.5150425114453892}, {"bbox": [201, 122, 302, 185], "label": "background", "iou": 0.1460043558384989}, {"bbox": [0, 0, 162, 216], "label": "background", "iou": 0.16766105785345578}, {"bbox": [0, 0, 400, 223], "label": "background", "iou": 0.26973063835021116}, {"bbox": [0, 25, 400, 400], "label": "background", "iou": 0.2312}, {"bbox": [207, 331, 281, 400], "label": "background", "iou": 0.0}, {"bbox": [138, 253, 166, 299], "label": "background", "iou": 0.008637128435221537}, {"bbox": [99, 294, 182, 335], "label": "background", "iou": 0.0}, {"bbox": [155, 33, 400, 400], "label": "background", "iou": 0.21360736375590514}, {"bbox": [250, 326, 325, 400], "label": "background", "iou": 0.0}, {"bbox": [0, 0, 223, 369], "label": "background", "iou": 0.2623654985592022}, {"bbox": [42, 225, 185, 371], "label": "background", "iou": 0.07957173114664905}, {"bbox": [207, 327, 323, 400], "label": "background", "iou": 0.0}, {"bbox": [0, 162, 203, 400], "label": "background", "iou": 0.1780888030888031}, {"bbox": [250, 321, 316, 400], "label": "background", "iou": 0.0}, {"bbox": [205, 133, 276, 185], "label": "background", "iou": 0.10645905420991926}, {"bbox": [205, 147, 276, 185], "label": "background", "iou": 0.07779700115340253}, {"bbox": [119, 95, 211, 184], "label": "background", "iou": 0.23610149942329872}, {"bbox": [195, 121, 292, 221], "label": "background", "iou": 0.2508455467869222}, {"bbox": [54, 57, 140, 155], "label": "background", "iou": 0.09278036909349016}, {"bbox": [80, 70, 335, 281], "label": "pothole", "iou": 0.6445497630331753}, {"bbox": [286, 298, 400, 400], "label": "background", "iou": 0.0}, {"bbox": [199, 124, 292, 189], "label": "background", "iou": 0.15696022727272727}, {"bbox": [87, 0, 400, 117], "label": "background", "iou": 0.06785981728321103}, {"bbox": [0, 47, 343, 400], "label": "background", "iou": 0.2864245657793672}, {"bbox": [118, 253, 172, 328], "label": "background", "iou": 0.015575833857772184}, {"bbox": [0, 33, 400, 400], "label": "background", "iou": 0.23623978201634876}, {"bbox": [0, 79, 165, 400], "label": "background", "iou": 0.19741785641095702}, {"bbox": [80, 70, 334, 239], "label": "pothole", "iou": 0.615916378628243}, {"bbox": [0, 70, 182, 380], "label": "background", "iou": 0.2350867678958785}, {"bbox": [118, 225, 203, 345], "label": "background", "iou": 0.07975460122699386}, {"bbox": [225, 132, 303, 185], "label": "background", "iou": 0.12572732458642327}, {"bbox": [0, 0, 400, 225], "label": "background", "iou": 0.27281636653191227}, {"bbox": [106, 0, 400, 171], "label": "background", "iou": 0.19237031214911296}, {"bbox": [62, 305, 136, 371], "label": "background", "iou": 0.0}, {"bbox": [48, 309, 136, 371], "label": "background", "iou": 0.0}, {"bbox": [155, 25, 400, 400], "label": "background", "iou": 0.2096057347670251}, {"bbox": [0, 0, 400, 342], "label": "background", "iou": 0.2535087719298246}, {"bbox": [127, 225, 185, 311], "label": "background", "iou": 0.06047158209912848}, {"bbox": [61, 134, 300, 281], "label": "pothole", "iou": 0.6125701614579724}, {"bbox": [0, 0, 223, 232], "label": "background", "iou": 0.29594193335532826}, {"bbox": [61, 46, 356, 281], "label": "pothole", "iou": 0.5002524341868013}, {"bbox": [0, 103, 160, 371], "label": "background", "iou": 0.19913419913419914}, {"bbox": [80, 70, 335, 260], "label": "pothole", "iou": 0.6873706004140787}, {"bbox": [0, 0, 163, 400], "label": "background", "iou": 0.1645097353386965}, {"bbox": [221, 33, 400, 400], "label": "background", "iou": 0.1194472636427512}, {"bbox": [185, 202, 374, 400], "label": "background", "iou": 0.0930507549572494}, {"bbox": [155, 176, 264, 345], "label": "background", "iou": 0.22046013468477788}, {"bbox": [42, 69, 343, 263], "label": "pothole", "iou": 0.5883477251783338}, {"bbox": [78, 77, 336, 239], "label": "pothole", "iou": 0.6307574206755373}, {"bbox": [0, 0, 164, 232], "label": "background", "iou": 0.18961004972520282}, {"bbox": [321, 92, 400, 342], "label": "background", "iou": 0.051495770579740044}, {"bbox": [261, 320, 371, 400], "label": "background", "iou": 0.0}, {"bbox": [286, 286, 400, 400], "label": "background", "iou": 0.0}, {"bbox": [173, 76, 311, 185], "label": "background", "iou": 0.2549405618232755}, {"bbox": [96, 0, 400, 171], "label": "background", "iou": 0.2005319443674849}, {"bbox": [76, 70, 334, 281], "label": "pothole", "iou": 0.6370549983467431}, {"bbox": [134, 95, 285, 221], "label": "pothole", "iou": 0.5430098258920876}, {"bbox": [0, 57, 400, 400], "label": "background", "iou": 0.25276967930029154}, {"bbox": [119, 95, 287, 239], "label": "pothole", "iou": 0.6766917293233082}, {"bbox": [0, 202, 203, 400], "label": "background", "iou": 0.113401142041399}, {"bbox": [78, 77, 336, 281], "label": "pothole", "iou": 0.6589147286821705}, {"bbox": [261, 297, 400, 400], "label": "background", "iou": 0.0}, {"bbox": [96, 0, 400, 213], "label": "background", "iou": 0.29031923176745394}, {"bbox": [199, 124, 282, 185], "label": "background", "iou": 0.1459919261822376}, {"bbox": [225, 25, 400, 185], "label": "background", "iou": 0.20475}, {"bbox": [0, 0, 223, 371], "label": "background", "iou": 0.261108664597274}, {"bbox": [173, 47, 343, 185], "label": "background", "iou": 0.24437340153452686}, {"bbox": [0, 0, 216, 214], "label": "background", "iou": 0.25269416573764397}, {"bbox": [0, 47, 400, 400], "label": "background", "iou": 0.24560906515580735}, {"bbox": [0, 79, 179, 400], "label": "background", "iou": 0.22347926542644306}, {"bbox": [0, 0, 224, 400], "label": "background", "iou": 0.24529058116232466}, {"bbox": [82, 70, 335, 278], "label": "pothole", "iou": 0.6483649271203081}, {"bbox": [122, 0, 400, 342], "label": "background", "iou": 0.2694294435313454}, {"bbox": [42, 176, 264, 371], "label": "background", "iou": 0.26209977661950856}, {"bbox": [42, 124, 292, 263], "label": "pothole", "iou": 0.6903637337488435}, {"bbox": [0, 184, 203, 369], "label": "background", "iou": 0.1577049443064348}, {"bbox": [0, 0, 216, 400], "label": "background", "iou": 0.236014699877501}, {"bbox": [0, 0, 164, 400], "label": "background", "iou": 0.16604651162790698}, {"bbox": [0, 70, 175, 400], "label": "background", "iou": 0.21171997902464604}, {"bbox": [153, 124, 292, 263], "label": "pothole", "iou": 0.5087449709432276}, {"bbox": [185, 171, 400, 400], "label": "background", "iou": 0.123239813674573}, {"bbox": [0, 0, 203, 400], "label": "background", "iou": 0.22017479203959145}, {"bbox": [0, 176, 264, 400], "label": "background", "iou": 0.20859527981036793}, {"bbox": [155, 76, 400, 400], "label": "background", "iou": 0.2380332139368284}, {"bbox": [0, 0, 182, 400], "label": "background", "iou": 0.19236742844464166}, {"bbox": [42, 0, 400, 400], "label": "background", "iou": 0.24217877094972068}, {"bbox": [0, 0, 185, 380], "label": "background", "iou": 0.2048662917479628}, {"bbox": [0, 0, 185, 400], "label": "background", "iou": 0.19652097324672466}]}